{
  "name": "Masse lourde",
  "type": "weapon",
  "img": "systems/liber-chronicles/assets/item/waepon/marteau.webp",
  "system": {
    "name": "Nouvel Objet",
    "biography": "<p>L'arme est perce armure.<br>Le porteur a un malus en défense de 20% .</p>",
    "quantity": 1,
    "degat": "1d8",
    "porter": "0",
    "poids": 5,
    "valeur": 250,
    "protec": 0,
    "class": "",
    "cible": "",
    "duree": "",
    "style": "melee",
    "doublemain": "no",
    "rayon": 0,
    "equip": "",
    "consommable": "no",
    "school": "aucune"
  },
  "effects": [],
  "folder": "eyESHvxjOQoNQSPq",
  "flags": {},
  "_stats": {
    "compendiumSource": "Compendium.liber-chronicles.inventaire.Item.oIMMfslnphFwQvnR",
    "duplicateSource": null,
    "exportSource": null,
    "coreVersion": "13.348",
    "systemId": "liber-chronicles",
    "systemVersion": "4.0.2",
    "createdTime": 1758885880253,
    "modifiedTime": 1758885880253,
    "lastModifiedBy": "aX7uFGXVamesf6ap"
  },
  "ownership": {
    "default": 0,
    "aX7uFGXVamesf6ap": 3
  },
  "_id": "cVNbJdnoIfeJileo",
  "sort": 0,
  "_key": "!items!cVNbJdnoIfeJileo"
}
