{
  "name": "Age végétal",
  "type": "magic",
  "img": "systems/liber-chronicles/assets/magie/nature-7.webp",
  "system": {
    "name": "Nouvel Objet",
    "biography": "<p>La cible prend conscience de l’importance de la nature, grâce au parfum d’une fleur magique, la cible doit faire un jet de mental, si elle échoue elle devient pacifiste et arrête toute action belliqueuse, toutes actions offensives à son égard, brisera le sort</p>",
    "quantity": 3,
    "degat": "0",
    "porter": "0",
    "rayon": 0,
    "poids": 0,
    "valeur": 0,
    "protec": 0,
    "class": "",
    "cible": "Cible",
    "duree": "Persistant",
    "style": "cc",
    "school": "natura",
    "equip": "",
    "consommable": "no",
    "doublemain": "no"
  },
  "effects": [],
  "folder": "hKAiortJ1gCcHTZi",
  "flags": {},
  "_stats": {
    "compendiumSource": "Compendium.liber-chronicles.magie.Item.py7lKJecYK7mObtV",
    "duplicateSource": null,
    "exportSource": null,
    "coreVersion": "13.348",
    "systemId": "liber-chronicles",
    "systemVersion": "4.0.2",
    "createdTime": 1758885888057,
    "modifiedTime": 1758885888057,
    "lastModifiedBy": "aX7uFGXVamesf6ap"
  },
  "ownership": {
    "default": 0,
    "aX7uFGXVamesf6ap": 3
  },
  "_id": "rbf87TrraXIcRHb6",
  "sort": 0,
  "_key": "!items!rbf87TrraXIcRHb6"
}
