{
  "name": "Appel sombre",
  "type": "magic",
  "img": "systems/liber-chronicles/assets/magie/sombre-15.webp",
  "system": {
    "name": "Nouvel Objet",
    "biography": "<p>Créer une zone de 20m où les ennemis ne peuvent pas voir et subissent un malus de 15% sur leur mental, concentration,</p><p><strong>Maintien : 2 psy</strong></p>",
    "quantity": 4,
    "degat": "0",
    "porter": "0",
    "rayon": 0,
    "poids": 0,
    "valeur": 0,
    "protec": 0,
    "class": "",
    "cible": "Cible",
    "duree": "Maintien",
    "style": "cc",
    "school": "dieuxsombres",
    "equip": "",
    "consommable": "no",
    "doublemain": "no"
  },
  "effects": [],
  "folder": "9QOAfr10cJjVNa0A",
  "ownership": {
    "default": 0,
    "eeeETIWwPcCQLmyP": 3
  },
  "flags": {},
  "_stats": {
    "compendiumSource": "Compendium.liber-chronicles.magie.Item.XVl5Y3P3aY7FcobJ",
    "duplicateSource": null,
    "exportSource": null,
    "coreVersion": "13.339",
    "systemId": "liber-chronicles",
    "systemVersion": "4.0.2",
    "createdTime": 1758800597777,
    "modifiedTime": 1758800597777,
    "lastModifiedBy": "eeeETIWwPcCQLmyP"
  },
  "_id": "iN6CYhGwxSvjSUWE",
  "sort": 0,
  "_key": "!items!iN6CYhGwxSvjSUWE"
}
